adafruit_ad569x.py
adafruit_circuitpython_ad569x-2.0.9.dist-info/licenses/LICENSE
adafruit_circuitpython_ad569x-2.0.9.dist-info/METADATA
adafruit_circuitpython_ad569x-2.0.9.dist-info/WHEEL
adafruit_circuitpython_ad569x-2.0.9.dist-info/top_level.txt
adafruit_circuitpython_ad569x-2.0.9.dist-info/RECORD
