Metadata-Version: 2.4
Name: adafruit-circuitpython-ad569x
Version: 2.0.9
Summary: CircuitPython driver for the AD569x DAC
Home-page: https://github.com/adafruit/Adafruit_CircuitPython_AD569x.git
Author: Adafruit Industries
Author-email: Adafruit Industries <circuitpython@adafruit.com>
License: MIT
Project-URL: Homepage, https://github.com/adafruit/Adafruit_CircuitPython_AD569x
Keywords: adafruit,blinka,circuitpython,micropython,ad569x,DAC
Classifier: Intended Audience :: Developers
Classifier: Topic :: Software Development :: Libraries
Classifier: Topic :: Software Development :: Embedded Systems
Classifier: Topic :: System :: Hardware
Classifier: License :: OSI Approved :: MIT License
Classifier: Programming Language :: Python :: 3
License-File: LICENSE
Requires-Dist: Adafruit-Blinka
Requires-Dist: adafruit-circuitpython-busdevice
Provides-Extra: optional
Dynamic: author
Dynamic: home-page
Dynamic: license-file
